gocart/__init__.py
gocart/__version__.py
gocart/advanced_settings.yaml
gocart/cl_utils.py
gocart/default_settings.yaml
gocart/setup.cfg
gocart/test_settings.yaml
gocart/utKit.py
gocart/commonutils/__init__.py
gocart/commonutils/flatten_healpix_map.py
gocart/commonutils/generate_skymap_stats.py
gocart/commonutils/getpackagepath.py
gocart/convert/__init__.py
gocart/convert/aitoff.py
gocart/convert/ascii.py
gocart/convert/healpix2cart.py
gocart/parsers/__init__.py
gocart/parsers/lvk.py
gocart/resources/package.mplstyle
gocart/resources/plugins/gp_template.py
gocart-0.4.8.dist-info/LICENSE
gocart-0.4.8.dist-info/METADATA
gocart-0.4.8.dist-info/WHEEL
gocart-0.4.8.dist-info/entry_points.txt
gocart-0.4.8.dist-info/top_level.txt
gocart-0.4.8.dist-info/RECORD
