Metadata-Version: 2.1
Name: gocart
Version: 0.4.8
Summary: Listen for, collect and convert multimessenger skymaps
Home-page: https://github.com/thespacedoctor/gocart
Download-URL: https://github.com/thespacedoctor/gocart/archive/v0.4.8.zip
Author: David Young
Author-email: d.r.young@qub.ac.uk
License: MIT
Keywords: astronomy
Classifier: Development Status :: 4 - Beta
Classifier: License :: OSI Approved :: MIT License
Classifier: Programming Language :: Python :: 3.11
Classifier: Topic :: Utilities
License-File: LICENSE
Requires-Dist: pyyaml
Requires-Dist: fundamentals
Requires-Dist: astropy (==5.2.0)
Requires-Dist: astropy-healpix
Requires-Dist: numpy
Requires-Dist: matplotlib
Requires-Dist: healpy
Requires-Dist: pandas
Requires-Dist: tabulate
Requires-Dist: gcn-kafka
Requires-Dist: mhealpy
